nonrelated_inlines/__init__.py
nonrelated_inlines/admin.py
nonrelated_inlines/forms.py
nonrelated_inlines/tests/__init__.py
nonrelated_inlines/tests/settings.py
nonrelated_inlines/tests/test_admin.py
nonrelated_inlines/tests/urls.py
nonrelated_inlines/tests/testapp/__init__.py
nonrelated_inlines/tests/testapp/admin.py
nonrelated_inlines/tests/testapp/models.py
nonrelated_inlines/tests/testapp/migrations/0001_initial.py
nonrelated_inlines/tests/testapp/migrations/__init__.py
django_nonrelated_inlines-0.2.dist-info/LICENSE
django_nonrelated_inlines-0.2.dist-info/METADATA
django_nonrelated_inlines-0.2.dist-info/WHEEL
django_nonrelated_inlines-0.2.dist-info/top_level.txt
django_nonrelated_inlines-0.2.dist-info/RECORD
